{"book":"1 Corinthians","book_id":"1-corinthians","chapter":8,"layer":"mystical_translation","relationship_to_restored_text":"Interpretive contemplative layer aligned by verse. This does not replace the source-audited restored translation.","verses":[{"verse":1,"mystical_translation":"Knowledge can inflate, but love builds the body."},{"verse":2,"mystical_translation":"Thinking you know may show you do not yet know rightly."},{"verse":3,"mystical_translation":"Loving the Divine means being known by the Divine."},{"verse":4,"mystical_translation":"The idol is nothing, and the Divine is one."},{"verse":5,"mystical_translation":"Many powers may be called gods and lords."},{"verse":6,"mystical_translation":"For us all things are from the one Divine and through the one Lord."},{"verse":7,"mystical_translation":"Not everyone experiences this knowledge without conscience-wounding."},{"verse":8,"mystical_translation":"Food does not increase or diminish our standing before the Divine."},{"verse":9,"mystical_translation":"Liberty must not become a stumbling block."},{"verse":10,"mystical_translation":"Knowledge displayed without love can train a tender conscience into harm."},{"verse":11,"mystical_translation":"A sibling for whom Messiah died can be damaged by your knowledge."},{"verse":12,"mystical_translation":"Wounding the sibling’s conscience wounds Messiah."},{"verse":13,"mystical_translation":"Love can abstain forever rather than make a sibling stumble."}],"contemplative_note":"1 Corinthians 8 makes love the test of knowledge. Correctness that wounds the body is not yet wisdom."}