{"book":"1 Corinthians","book_id":"1-corinthians","chapter":11,"layer":"mystical_translation","relationship_to_restored_text":"Interpretive contemplative layer aligned by verse. This does not replace the source-audited restored translation.","verses":[{"verse":1,"mystical_translation":"Imitation flows through Paul only as he imitates Messiah."},{"verse":2,"mystical_translation":"Tradition is held as received wisdom."},{"verse":3,"mystical_translation":"Head/source language frames ordered belonging before the Divine."},{"verse":4,"mystical_translation":"Prayer and prophecy carry visible honor."},{"verse":5,"mystical_translation":"Women pray and prophesy; Paul’s concern is public honor/order."},{"verse":6,"mystical_translation":"Covering language guards against shame within that setting."},{"verse":7,"mystical_translation":"Glory language is worked through creation imagery."},{"verse":8,"mystical_translation":"Paul recalls woman from man."},{"verse":9,"mystical_translation":"He recalls creation for relational purpose."},{"verse":10,"mystical_translation":"Authority upon the head remains a mysterious sign before messengers."},{"verse":11,"mystical_translation":"In the Lord, woman and man are not apart from each other."},{"verse":12,"mystical_translation":"Man is through woman, and all are from the Divine."},{"verse":13,"mystical_translation":"The community is asked to discern fitting practice."},{"verse":14,"mystical_translation":"Nature/custom imagery is invoked around hair and honor."},{"verse":15,"mystical_translation":"Hair becomes glory and covering imagery."},{"verse":16,"mystical_translation":"Contentiousness is not to rule the assemblies."},{"verse":17,"mystical_translation":"Their gatherings have become worse rather than better."},{"verse":18,"mystical_translation":"Splits appear even at assembly."},{"verse":19,"mystical_translation":"Factions reveal what is approved and what is fractured."},{"verse":20,"mystical_translation":"Their meal no longer truly functions as the Lord’s supper."},{"verse":21,"mystical_translation":"Some are hungry while others are drunk."},{"verse":22,"mystical_translation":"The poor are shamed at the very meal of the body."},{"verse":23,"mystical_translation":"Paul hands over the night of betrayal tradition."},{"verse":24,"mystical_translation":"Broken bread becomes body for you in remembrance."},{"verse":25,"mystical_translation":"The cup becomes new covenant in blood."},{"verse":26,"mystical_translation":"Eating and drinking proclaim the Lord’s death until he comes."},{"verse":27,"mystical_translation":"Unworthy participation violates body and blood."},{"verse":28,"mystical_translation":"Self-examination prepares the meal."},{"verse":29,"mystical_translation":"Judgment comes when the body is not discerned."},{"verse":30,"mystical_translation":"Weakness and sickness reveal communal disorder."},{"verse":31,"mystical_translation":"Discernment would spare judgment."},{"verse":32,"mystical_translation":"Discipline aims to prevent condemnation with the world."},{"verse":33,"mystical_translation":"Wait for one another."},{"verse":34,"mystical_translation":"Eat at home if hungry; the assembly meal must not become judgment."}],"contemplative_note":"1 Corinthians 11 is about embodied honor and table justice. Women are praying and prophesying; the Lord’s supper fails when the poor are humiliated and the body is not discerned."}