{"book":"1 Samuel","book_id":"1-samuel","chapter":17,"layer":"mystical_translation","relationship_to_restored_text":"Interpretive contemplative layer aligned by verse. This does not replace the source-audited restored translation.","verses":[{"verse":1,"mystical_translation":"War gathers on contested ground before any hero enters the story."},{"verse":2,"mystical_translation":"Saul and Israel arrange themselves against Philistine power."},{"verse":3,"mystical_translation":"Two armies face one another across a valley of fear."},{"verse":4,"mystical_translation":"Goliath emerges as the embodied weight of military intimidation."},{"verse":5,"mystical_translation":"Bronze and scale armor turn one body into a spectacle of force."},{"verse":6,"mystical_translation":"Every limb is framed by weaponry."},{"verse":7,"mystical_translation":"Even his spear requires another human system to carry and shield him."},{"verse":8,"mystical_translation":"He reduces whole peoples to servants through a proposed duel."},{"verse":9,"mystical_translation":"The wager treats human communities as possessions of whichever fighter survives."},{"verse":10,"mystical_translation":"Defiance becomes public pressure for one body to carry a nation's fate."},{"verse":11,"mystical_translation":"Saul and Israel are shattered by what they hear; fear is not hidden."},{"verse":12,"mystical_translation":"David enters from an aging Bethlehem household, not from the military center."},{"verse":13,"mystical_translation":"His older brothers already belong to Saul's war system."},{"verse":14,"mystical_translation":"The youngest remains between family labor and royal service."},{"verse":15,"mystical_translation":"David moves back and forth, tending life while war waits."},{"verse":16,"mystical_translation":"Threat becomes ritual through forty days of morning and evening intimidation."},{"verse":17,"mystical_translation":"Jesse sends nourishment, not weapons, through David's hands."},{"verse":18,"mystical_translation":"Food, family well-being, and proof of life connect home to the front."},{"verse":19,"mystical_translation":"The household's care reaches into a valley organized for killing."},{"verse":20,"mystical_translation":"David entrusts the flock and arrives as the army raises its cry."},{"verse":21,"mystical_translation":"Rank faces rank, each side mirroring the other."},{"verse":22,"mystical_translation":"He leaves his burden with a keeper and runs first toward his brothers."},{"verse":23,"mystical_translation":"The champion repeats his words, and David finally hears the machinery of fear."},{"verse":24,"mystical_translation":"The soldiers flee; survival instinct moves through the whole line."},{"verse":25,"mystical_translation":"The king answers danger with wealth, marriage, and household privilege."},{"verse":26,"mystical_translation":"David hears both insult and a crisis of trust, speaking from covenant identity."},{"verse":27,"mystical_translation":"The crowd repeats the royal reward as though reward could settle the moral question."},{"verse":28,"mystical_translation":"Eliab converts fear and rivalry into contempt for his younger brother."},{"verse":29,"mystical_translation":"David refuses the accusation and keeps his voice."},{"verse":30,"mystical_translation":"He turns away from shaming and continues asking."},{"verse":31,"mystical_translation":"Words from the margin reach the king."},{"verse":32,"mystical_translation":"David offers himself where trained soldiers have been immobilized."},{"verse":33,"mystical_translation":"Saul sees the obvious danger: a youth facing a lifelong warrior."},{"verse":34,"mystical_translation":"David answers from prior encounters protecting vulnerable animals."},{"verse":35,"mystical_translation":"His shepherding story already contains rescue and lethal force intertwined."},{"verse":36,"mystical_translation":"He interprets the military threat through those remembered struggles."},{"verse":37,"mystical_translation":"Trust becomes the ground of his willingness, and Saul releases him into danger."},{"verse":38,"mystical_translation":"Royal armor tries to make David into a smaller version of Saul."},{"verse":39,"mystical_translation":"David refuses equipment that does not belong to his embodied knowledge."},{"verse":40,"mystical_translation":"He approaches with ordinary shepherd tools and carefully chosen stones."},{"verse":41,"mystical_translation":"The armed system advances behind its shield."},{"verse":42,"mystical_translation":"Goliath despises what does not resemble sanctioned military power."},{"verse":43,"mystical_translation":"Body, youth, sticks, and gods become weapons of ridicule."},{"verse":44,"mystical_translation":"Threat expands beyond death into exposure of the body."},{"verse":45,"mystical_translation":"David answers military technology with the name he trusts."},{"verse":46,"mystical_translation":"His reply also enters the language of killing, beheading, and exposed corpses."},{"verse":47,"mystical_translation":"The assembly is told that deliverance does not belong to weapon systems, even as battle continues."},{"verse":48,"mystical_translation":"David runs into the narrow space where decision becomes irreversible."},{"verse":49,"mystical_translation":"A small stone penetrates the spectacle of armor, and the champion falls."},{"verse":50,"mystical_translation":"The sling defeats the sword-bearer before David possesses a sword."},{"verse":51,"mystical_translation":"David takes the fallen man's weapon and completes the killing with beheading."},{"verse":52,"mystical_translation":"One death opens mass flight, pursuit, and many more wounded bodies."},{"verse":53,"mystical_translation":"Victory becomes plunder when the pursuers return."},{"verse":54,"mystical_translation":"The severed head and weapons become trophies carried into later memory."},{"verse":55,"mystical_translation":"Saul asks not merely who David is, but which household now stands before royal power."},{"verse":56,"mystical_translation":"The king seeks the youth's lineage."},{"verse":57,"mystical_translation":"David returns holding the visible violence that made him famous."},{"verse":58,"mystical_translation":"He names himself through Jesse of Bethlehem, returning the hero to a family."}],"contemplative_note":"The contemplative center is not that a small believer can always crush a giant. It is that militarized spectacle can monopolize imagination until one person sees another possibility—yet that possibility still passes through lethal violence, beheading, pursuit, and plunder. Courage must never be severed from protection of children, restraint of weapons, refusal of body shame, and accountability after victory."}