{"book":"Acts","book_id":"acts","chapter":11,"layer":"mystical_translation","relationship_to_restored_text":"Interpretive contemplative layer aligned by verse. This does not replace the source-audited restored translation.","verses":[{"verse":1,"mystical_translation":"Judea hears that the nations received the word."},{"verse":2,"mystical_translation":"Peter is challenged by circumcision-boundary concern."},{"verse":3,"mystical_translation":"The objection is table fellowship across boundary."},{"verse":4,"mystical_translation":"Peter explains in order."},{"verse":5,"mystical_translation":"He recounts the heaven-sheet vision in prayer."},{"verse":6,"mystical_translation":"He observes the creatures gathered into the vessel."},{"verse":7,"mystical_translation":"The voice commands rise and eat."},{"verse":8,"mystical_translation":"Peter resists common and unclean."},{"verse":9,"mystical_translation":"Heaven answers: do not common what the Divine cleansed."},{"verse":10,"mystical_translation":"Threefold repetition seals the message."},{"verse":11,"mystical_translation":"Three sent men arrive immediately."},{"verse":12,"mystical_translation":"The Spirit commands no distinction, and six siblings witness the crossing."},{"verse":13,"mystical_translation":"Cornelius’ messenger story is retold."},{"verse":14,"mystical_translation":"Words will bring saving/healing to the whole house."},{"verse":15,"mystical_translation":"As Peter begins, Spirit falls as at the beginning."},{"verse":16,"mystical_translation":"The Lord’s word about Spirit baptism is remembered."},{"verse":17,"mystical_translation":"The equal gift means Peter cannot hinder the Divine."},{"verse":18,"mystical_translation":"The assembly quiets and glorifies: the nations receive turning into life."},{"verse":19,"mystical_translation":"Stephen’s persecution scatters witness as far as Antioch."},{"verse":20,"mystical_translation":"Some speak good news to Greeks also."},{"verse":21,"mystical_translation":"The Lord’s hand is with them, and many turn."},{"verse":22,"mystical_translation":"Jerusalem sends Barnabas to Antioch."},{"verse":23,"mystical_translation":"Barnabas sees grace and encourages purpose of heart."},{"verse":24,"mystical_translation":"Full of Spirit and trust, Barnabas gathers more to the Lord."},{"verse":25,"mystical_translation":"He seeks Saul in Tarsus."},{"verse":26,"mystical_translation":"Antioch becomes a year-long teaching center and naming-place."},{"verse":27,"mystical_translation":"Prophets arrive from Jerusalem."},{"verse":28,"mystical_translation":"Agabus signals famine through the Spirit."},{"verse":29,"mystical_translation":"The disciples respond according to means for Judean siblings."},{"verse":30,"mystical_translation":"Barnabas and Saul carry the service to the elders."}]}