{"book":"Luke","book_id":"luke","chapter":14,"layer":"mystical_translation","relationship_to_restored_text":"Interpretive contemplative layer aligned by verse. This does not replace the source-audited restored translation.","verses":[{"verse":1,"mystical_translation":"A Sabbath meal becomes a watched space."},{"verse":2,"mystical_translation":"A man in visible need stands before Jesus."},{"verse":3,"mystical_translation":"Jesus asks whether Sabbath permits healing."},{"verse":4,"mystical_translation":"Silence gives way to healing and release."},{"verse":5,"mystical_translation":"Mercy pulls child or ox from the well on Sabbath."},{"verse":6,"mystical_translation":"They cannot answer mercy."},{"verse":7,"mystical_translation":"Jesus notices status-seeking at the table."},{"verse":8,"mystical_translation":"Do not seize the first place."},{"verse":9,"mystical_translation":"Self-exaltation can end in shame."},{"verse":10,"mystical_translation":"The last place leaves room for gift."},{"verse":11,"mystical_translation":"Exaltation and humility reverse."},{"verse":12,"mystical_translation":"Hospitality aimed at repayment stays trapped in exchange."},{"verse":13,"mystical_translation":"The banquet of the reign welcomes those without repayment power."},{"verse":14,"mystical_translation":"Blessing comes when giving cannot be paid back."},{"verse":15,"mystical_translation":"Someone blesses eating bread in the Divine reign."},{"verse":16,"mystical_translation":"A great dinner is prepared and many are invited."},{"verse":17,"mystical_translation":"The ready feast calls the invited."},{"verse":18,"mystical_translation":"A field becomes excuse."},{"verse":19,"mystical_translation":"Oxen become excuse."},{"verse":20,"mystical_translation":"Marriage becomes excuse."},{"verse":21,"mystical_translation":"The invitation turns toward the poor, disabled, blind, and lame."},{"verse":22,"mystical_translation":"There is still room."},{"verse":23,"mystical_translation":"The house must be filled from roads and hedges."},{"verse":24,"mystical_translation":"Those who refuse the invitation miss the feast."},{"verse":25,"mystical_translation":"Great crowds require honest discipleship teaching."},{"verse":26,"mystical_translation":"Following reorders even the deepest family and self-attachments."},{"verse":27,"mystical_translation":"The disciple carries the cross after him."},{"verse":28,"mystical_translation":"A tower asks for cost counted first."},{"verse":29,"mystical_translation":"Unfinished foundation becomes public mockery."},{"verse":30,"mystical_translation":"Beginning without finishing is exposed."},{"verse":31,"mystical_translation":"A king must deliberate before battle."},{"verse":32,"mystical_translation":"Peace is sought before ruin when strength is lacking."},{"verse":33,"mystical_translation":"Possessions must lose their claim over discipleship."},{"verse":34,"mystical_translation":"Salt is good when it remains salty."},{"verse":35,"mystical_translation":"Ears are called again to hear."}]}