{"book":"Revelation","book_id":"revelation","chapter":16,"layer":"mystical_translation","relationship_to_restored_text":"Interpretive contemplative layer aligned by verse. This does not replace the source-audited restored translation.","verses":[{"verse":1,"mystical_translation":"Seven bowls are poured as completed symbolic judgment."},{"verse":2,"mystical_translation":"Beast-mark allegiance becomes painful exposure."},{"verse":3,"mystical_translation":"The sea bears the sign of death."},{"verse":4,"mystical_translation":"Rivers and springs become witness."},{"verse":5,"mystical_translation":"The waters' messenger names Divine justice."},{"verse":6,"mystical_translation":"The spilled life of witnesses is remembered."},{"verse":7,"mystical_translation":"The altar agrees: true and just are the judgments."},{"verse":8,"mystical_translation":"The sun becomes a sign of scorching exposure."},{"verse":9,"mystical_translation":"Hardened hearts blame instead of turn."},{"verse":10,"mystical_translation":"The beast-throne darkens."},{"verse":11,"mystical_translation":"Pain does not become repentance."},{"verse":12,"mystical_translation":"Euphrates dries for symbolic gathering."},{"verse":13,"mystical_translation":"Frog-like spirits emerge from dragon, beast, and false prophet."},{"verse":14,"mystical_translation":"False signs gather kings into conflict."},{"verse":15,"mystical_translation":"Stay awake and keep your garments."},{"verse":16,"mystical_translation":"The gathering place is called Harmagedon."},{"verse":17,"mystical_translation":"The final bowl declares: it has happened."},{"verse":18,"mystical_translation":"Creation shakes under the sign."},{"verse":19,"mystical_translation":"Babylon is remembered before Divine."},{"verse":20,"mystical_translation":"Islands and mountains vanish from the old order."},{"verse":21,"mystical_translation":"Even severe signs do not soften hardened speech."}],"contemplative_note":"Revelation 16 is the hardening mirror: plagues expose allegiance, propaganda gathers power, and the watcher is told to stay awake."}