{"book":"Mark","book_id":"mark","chapter":5,"layer":"mystical_translation","relationship_to_restored_text":"Interpretive contemplative layer aligned by verse. This does not replace the source-audited restored translation.","verses":[{"verse":1,"mystical_translation":"Jesus crosses into Gerasene territory."},{"verse":2,"mystical_translation":"From the tombs, a tormented man meets him immediately."},{"verse":3,"mystical_translation":"He lives among death-spaces where ordinary restraint has failed."},{"verse":4,"mystical_translation":"Human binding could not bring healing."},{"verse":5,"mystical_translation":"Night and day his pain echoes among tombs and mountains."},{"verse":6,"mystical_translation":"From far off, he runs and bows before Jesus."},{"verse":7,"mystical_translation":"The hidden forces recognize the Son of the Most High."},{"verse":8,"mystical_translation":"Jesus commands release from the man."},{"verse":9,"mystical_translation":"The name Legion reveals a fragmented multitude."},{"verse":10,"mystical_translation":"The forces plead not to be sent from the region."},{"verse":11,"mystical_translation":"A large herd feeds nearby."},{"verse":12,"mystical_translation":"They ask to enter the herd."},{"verse":13,"mystical_translation":"The disorder leaves the man and rushes toward the sea."},{"verse":14,"mystical_translation":"The keepers report what happened."},{"verse":15,"mystical_translation":"The man is found seated, clothed, and sound-minded; restoration frightens the onlookers."},{"verse":16,"mystical_translation":"Witnesses tell the story."},{"verse":17,"mystical_translation":"The region asks Jesus to leave."},{"verse":18,"mystical_translation":"The restored man wants to remain with him."},{"verse":19,"mystical_translation":"Jesus sends him home as a witness of mercy."},{"verse":20,"mystical_translation":"He proclaims in the Decapolis what Jesus has done."},{"verse":21,"mystical_translation":"Jesus crosses back and the crowd gathers again."},{"verse":22,"mystical_translation":"Jairus falls at his feet."},{"verse":23,"mystical_translation":"A father asks for touch so his daughter may live."},{"verse":24,"mystical_translation":"Jesus goes with him through the pressing crowd."},{"verse":25,"mystical_translation":"A woman has carried a flow of blood for twelve years."},{"verse":26,"mystical_translation":"She has spent everything and suffered without healing."},{"verse":27,"mystical_translation":"She reaches from behind to touch his garment."},{"verse":28,"mystical_translation":"Her trust says touch is enough."},{"verse":29,"mystical_translation":"Immediately her body knows healing."},{"verse":30,"mystical_translation":"Jesus feels power go out and seeks the one who touched."},{"verse":31,"mystical_translation":"The disciples see only the crowd pressure."},{"verse":32,"mystical_translation":"Jesus looks for the person inside the crowd."},{"verse":33,"mystical_translation":"The woman comes trembling and tells the whole truth."},{"verse":34,"mystical_translation":"He calls her daughter and sends her into peace and wholeness."},{"verse":35,"mystical_translation":"News of death arrives before Jairus’ request is complete."},{"verse":36,"mystical_translation":"Jesus answers fear with trust."},{"verse":37,"mystical_translation":"Only the inner three continue with him."},{"verse":38,"mystical_translation":"The house is full of mourning."},{"verse":39,"mystical_translation":"Jesus speaks of sleep where others see finality."},{"verse":40,"mystical_translation":"He clears the room and enters with parents and witnesses."},{"verse":41,"mystical_translation":"Taking her hand, he speaks Aramaic life: Little girl, rise."},{"verse":42,"mystical_translation":"Immediately the twelve-year-old rises and walks."},{"verse":43,"mystical_translation":"He protects the mystery and asks that she be fed."}]}