{"book":"Joshua","book_id":"joshua","chapter":12,"layer":"mystical_translation","relationship_to_restored_text":"Interpretive contemplative layer aligned by verse. This does not replace the source-audited restored translation.","verses":[{"verse":1,"mystical_translation":"The chapter turns war into a geographic register of defeated rulers."},{"verse":2,"mystical_translation":"Sihon's territory is mapped from Arnon toward Jabbok and Gilead."},{"verse":3,"mystical_translation":"Arabah, Chinneroth, Salt Sea, and Pisgah complete the eastern boundary."},{"verse":4,"mystical_translation":"Og is remembered as a remaining Rephaim king at Ashtaroth and Edrei."},{"verse":5,"mystical_translation":"Hermon, Salecah, Bashan, and Gilead define his domain."},{"verse":6,"mystical_translation":"Moses' victories become inheritance for Reuben, Gad, and half Manasseh."},{"verse":7,"mystical_translation":"Joshua's western victories are mapped from Lebanon's valley toward Seir."},{"verse":8,"mystical_translation":"Hill, lowland, wilderness, and southland become categories of possession."},{"verse":9,"mystical_translation":"Jericho and Ai are reduced to one king each."},{"verse":10,"mystical_translation":"Jerusalem and Hebron become two more counted outcomes."},{"verse":11,"mystical_translation":"Jarmuth and Lachish enter the list."},{"verse":12,"mystical_translation":"Eglon and Gezer follow."},{"verse":13,"mystical_translation":"Debir and Geder are counted."},{"verse":14,"mystical_translation":"Hormah and Arad are counted."},{"verse":15,"mystical_translation":"Libnah and Adullam are counted."},{"verse":16,"mystical_translation":"Makkedah and Bethel are counted."},{"verse":17,"mystical_translation":"Tappuah and Hepher are counted."},{"verse":18,"mystical_translation":"Aphek and Lasharon are counted."},{"verse":19,"mystical_translation":"Madon and Hazor are counted."},{"verse":20,"mystical_translation":"Shimron-meron and Achshaph are counted."},{"verse":21,"mystical_translation":"Taanach and Megiddo are counted."},{"verse":22,"mystical_translation":"Kedesh and Jokneam are counted."},{"verse":23,"mystical_translation":"Dor and Goiim in Gilgal are counted."},{"verse":24,"mystical_translation":"Tirzah completes the total of thirty-one kings."}],"contemplative_note":"Joshua 12 demonstrates how administration can make violence look clean. A city becomes a king, a campaign becomes a number, and a people disappears into a list. Ethical memory must restore the human lives that victory records omit."}