{"book":"Exodus","book_id":"exodus","chapter":3,"layer":"mystical_translation","relationship_to_restored_text":"Interpretive contemplative layer aligned by verse. This does not replace the source-audited restored translation.","verses":[{"verse":1,"mystical_translation":"Moses shepherds beyond the wilderness and arrives at the mountain of Divine."},{"verse":2,"mystical_translation":"Fire burns in the bush, yet the bush is not consumed."},{"verse":3,"mystical_translation":"Moses turns aside toward wonder."},{"verse":4,"mystical_translation":"When he turns, the Divine calls his name from the flame."},{"verse":5,"mystical_translation":"Sandals come off because wilderness ground has become holy."},{"verse":6,"mystical_translation":"The ancestral Divine speaks, and Moses hides his face."},{"verse":7,"mystical_translation":"YHWH sees affliction, hears the cry, and knows the pain."},{"verse":8,"mystical_translation":"The Divine comes down to rescue and bring up into spaciousness."},{"verse":9,"mystical_translation":"The cry has arrived; oppression is seen."},{"verse":10,"mystical_translation":"Moses is sent to Pharaoh for liberation."},{"verse":11,"mystical_translation":"Moses asks, Who am I?"},{"verse":12,"mystical_translation":"The answer is presence: I will be with you."},{"verse":13,"mystical_translation":"Moses asks for the Name."},{"verse":14,"mystical_translation":"The Name opens as I AM / I WILL BE."},{"verse":15,"mystical_translation":"YHWH is remembered from generation to generation."},{"verse":16,"mystical_translation":"The elders are gathered around the visitation of YHWH."},{"verse":17,"mystical_translation":"Affliction will be lifted toward milk-and-honey spaciousness."},{"verse":18,"mystical_translation":"The elders go with Moses to ask for wilderness worship."},{"verse":19,"mystical_translation":"YHWH knows Pharaoh will resist."},{"verse":20,"mystical_translation":"Wonders will break open the sending-away."},{"verse":21,"mystical_translation":"The people will not leave empty."},{"verse":22,"mystical_translation":"The wealth of oppression is drawn out for the children."}],"contemplative_note":"Exodus 3 is the flame of liberation: holy ground, the Name as presence, and the Divine who sees, hears, knows, comes down, and sends."}